pygethub/__init__.py
pygethub/_version.py
pygethub/exceptions.py
pygethub/paginator.py
pygethub/resources.py
pygethub-0.1.2.dist-info/LICENSE
pygethub-0.1.2.dist-info/METADATA
pygethub-0.1.2.dist-info/WHEEL
pygethub-0.1.2.dist-info/top_level.txt
pygethub-0.1.2.dist-info/RECORD
