Metadata-Version: 2.1
Name: pygethub
Version: 0.1.2
Summary: Fetch data from GitHub
Author-email: "@chrisammon3000" <gclindsey@gmail.com>
License: MIT License
Keywords: github,api,fetch,data,json
Classifier: Development Status :: 3 - Alpha
Classifier: License :: OSI Approved :: MIT License
Classifier: Operating System :: OS Independent
Classifier: Programming Language :: Python :: 3.10
Classifier: Topic :: Software Development :: Libraries :: Python Modules
Classifier: Topic :: Utilities
Requires-Python: >=3.8
License-File: LICENSE
Requires-Dist: requests >=2.22.0
Provides-Extra: dev
Requires-Dist: black >=21.12 ; extra == 'dev'
Provides-Extra: test
Requires-Dist: pytest >=6.2 ; extra == 'test'
Requires-Dist: pytest-cov >=3.0 ; extra == 'test'
Requires-Dist: coverage >=6.0 ; extra == 'test'
